Workbook
Name Accounts: Sheet1!$A$2:$B$34
Name AccountsList: Sheet1!$A$2:$A$581
Name ListAccounts: Sheet1!$A$2:$A$33
Name Mylist: Sheet2!$A$2:$A$26

Sheet Accrual Tagging
A1: Account Code | B1: Account | C1: Amount | D1: Category
A2: =IF(B2="","",IFERROR(VLOOKUP(TRIM(B2),Sheet1!A:B,2,FALSE),"")) | E2: =IF(D2="","",IFERROR(VLOOKUP(TRIM(D2),Sheet2!A:B,2,FALSE),""))
A3: =IF(B3="","",IFERROR(VLOOKUP(TRIM(B3),Sheet1!A:B,2,FALSE),"")) | E3: =IF(D3="","",IFERROR(VLOOKUP(TRIM(D3),Sheet2!A:B,2,FALSE),""))
A4: =IF(B4="","",IFERROR(VLOOKUP(TRIM(B4),Sheet1!A:B,2,FALSE),"")) | E4: =IF(D4="","",IFERROR(VLOOKUP(TRIM(D4),Sheet2!A:B,2,FALSE),""))
A5: =IF(B5="","",IFERROR(VLOOKUP(TRIM(B5),Sheet1!A:B,2,FALSE),"")) | E5: =IF(D5="","",IFERROR(VLOOKUP(TRIM(D5),Sheet2!A:B,2,FALSE),""))
A6: =IF(B6="","",IFERROR(VLOOKUP(TRIM(B6),Sheet1!A:B,2,FALSE),"")) | E6: =IF(D6="","",IFERROR(VLOOKUP(TRIM(D6),Sheet2!A:B,2,FALSE),""))
A7: =IF(B7="","",IFERROR(VLOOKUP(TRIM(B7),Sheet1!A:B,2,FALSE),"")) | E7: =IF(D7="","",IFERROR(VLOOKUP(TRIM(D7),Sheet2!A:B,2,FALSE),""))
A8: =IF(B8="","",IFERROR(VLOOKUP(TRIM(B8),Sheet1!A:B,2,FALSE),"")) | E8: =IF(D8="","",IFERROR(VLOOKUP(TRIM(D8),Sheet2!A:B,2,FALSE),""))
A9: =IF(B9="","",IFERROR(VLOOKUP(TRIM(B9),Sheet1!A:B,2,FALSE),"")) | E9: =IF(D9="","",IFERROR(VLOOKUP(TRIM(D9),Sheet2!A:B,2,FALSE),""))
A10: =IF(B10="","",IFERROR(VLOOKUP(TRIM(B10),Sheet1!A:B,2,FALSE),"")) | E10: =IF(D10="","",IFERROR(VLOOKUP(TRIM(D10),Sheet2!A:B,2,FALSE),""))
A11: =IF(B11="","",IFERROR(VLOOKUP(TRIM(B11),Sheet1!A:B,2,FALSE),"")) | E11: =IF(D11="","",IFERROR(VLOOKUP(TRIM(D11),Sheet2!A:B,2,FALSE),""))
A12: =IF(B12="","",IFERROR(VLOOKUP(TRIM(B12),Sheet1!A:B,2,FALSE),"")) | E12: =IF(D12="","",IFERROR(VLOOKUP(TRIM(D12),Sheet2!A:B,2,FALSE),""))
A13: =IF(B13="","",IFERROR(VLOOKUP(TRIM(B13),Sheet1!A:B,2,FALSE),"")) | E13: =IF(D13="","",IFERROR(VLOOKUP(TRIM(D13),Sheet2!A:B,2,FALSE),""))
... A15: =IF(B15="","",IFERROR(VLOOKUP(TRIM(B15),Sheet1!A:B,2,FALSE),"")) | E15: =IF(D15="","",IFERROR(VLOOKUP(TRIM(D15),Sheet2!A:B,2,FALSE),""))
E16: =IF(D16="","",IFERROR(VLOOKUP(TRIM(D16),Sheet2!A:B,2,FALSE),""))
E17: =IF(D17="","",IFERROR(VLOOKUP(TRIM(D17),Sheet2!A:B,2,FALSE),""))
E18: =IF(D18="","",IFERROR(VLOOKUP(TRIM(D18),Sheet2!A:B,2,FALSE),""))
E19: =IF(D19="","",IFERROR(VLOOKUP(TRIM(D19),Sheet2!A:B,2,FALSE),""))
E20: =IF(D20="","",IFERROR(VLOOKUP(TRIM(D20),Sheet2!A:B,2,FALSE),""))
E21: =IF(D21="","",IFERROR(VLOOKUP(TRIM(D21),Sheet2!A:B,2,FALSE),""))
E22: =IF(D22="","",IFERROR(VLOOKUP(TRIM(D22),Sheet2!A:B,2,FALSE),""))
E23: =IF(D23="","",IFERROR(VLOOKUP(TRIM(D23),Sheet2!A:B,2,FALSE),""))
E24: =IF(D24="","",IFERROR(VLOOKUP(TRIM(D24),Sheet2!A:B,2,FALSE),""))
E25: =IF(D25="","",IFERROR(VLOOKUP(TRIM(D25),Sheet2!A:B,2,FALSE),""))
E26: =IF(D26="","",IFERROR(VLOOKUP(TRIM(D26),Sheet2!A:B,2,FALSE),""))
E27: =IF(D27="","",IFERROR(VLOOKUP(TRIM(D27),Sheet2!A:B,2,FALSE),""))
... E132: =IF(D132="","",IFERROR(VLOOKUP(TRIM(D132),Sheet2!A:B,2,FALSE),""))

Sheet Sheet1
A1: Accounts | B1: Code
A2: Accrued Inventory | B2: 2110110
A3: Accrued Interest On Promissory Note | B3: 2110200
A4: Accrued Interest On Med-Term Loan | B4: 2110300
A5: Accrued Interest On Other Loans | B5: 2110400
A6: Accrued Utility Cost | B6: 2110500
A7: Accrued Facility Cost | B7: 2110600
A8: Accrued Sales Commission | B8: 2110700
A9: Accrued Consultancy Fees | B9: 2110800
A10: Accrued Audit Fees | B10: 2110900
A11: Accrued N2/H2 | B11: 2111100
A12: Accrued Contract Services | B12: 2111200
A13: Accrued Freight | B13: 2111300
... A34: Accrued DL | B34: 2113000

Sheet Sheet2
A1: Category | B1: Category ID
A2: POWER | B2: 1
A3: COMMUNICATION TELEPHONE | B3: 2
A4: RENTAL GLACIER | B4: 3
A5: RENTAL FTI | B5: 4
A6: COMMUNICATION INTERNET | B6: 5
